{"cameraMode":{"drawMode":0,"name":"Shaded","section":"Shading Mode"},"sceneLighting":true,"audioPlay":false,"sceneViewState":{"m_AlwaysRefresh":false,"showFog":true,"showSkybox":true,"showFlares":true,"showImageEffects":true,"showParticleSystems":true,"showVisualEffectGraphs":true,"m_FxEnabled":true},"in2DMode":false,"pivot":{"x":11.621891975402832,"y":-7.15901517868042,"z":-83.50083923339844},"rotation":{"x":-0.0002921369450632483,"y":-0.9972527027130127,"z":0.07433094829320908,"w":-0.004190726205706596},"size":38.653968811035159,"orthographic":false}